{
    "0": {
        "id": 3,
        "site": " Battle of Chefs 2020 ",
        "date": "2020-04-18 06:00"
    },
    "1": {
        "id": 2,
        "site": " AtCoder Beginner Contest 163 ",
        "date": "2020-04-19 12:00"
    },
    "2": {
        "id": 3,
        "site": " April Cook-Off 2020 ",
        "date": "2020-04-19 16:00"
    },
    "3": {
        "id": 1,
        "site": " Codeforces Round #636 (Div. 3) ",
        "date": "2020-04-21 14:35"
    },
    "4": {
        "id": 1,
        "site": " Codeforces Round #637 (Div. 2) ",
        "date": "2020-04-23 14:35"
    },
    "5": {
        "id": 1,
        "site": " Codeforces Round #637 (Div. 1) ",
        "date": "2020-04-23 14:35"
    },
    "6": {
        "id": 3,
        "site": " April Lunchtime 2020 ",
        "date": "2020-04-25 14:00"
    },
    "7": {
        "id": 1,
        "site": " Educational Codeforces Round 86 (рейтинговый для Див. 2) ",
        "date": "2020-04-26 14:35"
    },
    "8": {
        "id": 3,
        "site": " Quarantest Contest ",
        "date": "2020-04-30 13:30"
    },
    "9": {
        "id": 3,
        "site": " May Challenge 2020 ",
        "date": "2020-05-01 09:30"
    },
    "10": {
        "id": 3,
        "site": " May Cook-Off 2020 ",
        "date": "2020-05-17 16:00"
    },
    "11": {
        "id": 3,
        "site": " May Lunchtime 2020 ",
        "date": "2020-05-23 14:00"
    },
    "12": {
        "id": 3,
        "site": " June Challenge 2020 ",
        "date": "2020-06-05 09:30"
    },
    "13": {
        "id": 3,
        "site": " June Cook-Off 2020 ",
        "date": "2020-06-21 16:00"
    },
    "14": {
        "id": 3,
        "site": " June Lunchtime 2020 ",
        "date": "2020-06-27 14:00"
    },
    "15": {
        "id": 3,
        "site": " July Challenge 2020 ",
        "date": "2020-07-03 09:30"
    },
    "16": {
        "id": 3,
        "site": " July Cook-Off 2020 ",
        "date": "2020-07-19 16:00"
    },
    "17": {
        "id": 3,
        "site": " July Lunchtime 2020 ",
        "date": "2020-07-25 14:00"
    },
    "18": {
        "id": 3,
        "site": " August Challenge 2020 ",
        "date": "2020-08-07 09:30"
    },
    "19": {
        "id": 3,
        "site": " August Cook-Off 2020 ",
        "date": "2020-08-16 16:00"
    },
    "20": {
        "id": 3,
        "site": " August Lunchtime 2020 ",
        "date": "2020-08-22 14:00"
    },
    "21": {
        "id": 3,
        "site": " September Challenge 2020 ",
        "date": "2020-09-04 09:30"
    },
    "22": {
        "id": 3,
        "site": " September Cook-Off 2020 ",
        "date": "2020-09-20 16:00"
    },
    "23": {
        "id": 3,
        "site": " September Lunchtime 2020 ",
        "date": "2020-09-26 14:00"
    },
    "24": {
        "id": 3,
        "site": " October Challenge 2020 ",
        "date": "2020-10-02 09:30"
    },
    "25": {
        "id": 3,
        "site": " October Cook-Off 2020 ",
        "date": "2020-10-18 16:00"
    },
    "26": {
        "id": 3,
        "site": " October Lunchtime 2020 ",
        "date": "2020-10-24 14:00"
    },
    "27": {
        "id": 3,
        "site": " November Challenge 2020 ",
        "date": "2020-11-06 09:30"
    },
    "28": {
        "id": 3,
        "site": " November Cook-Off 2020 ",
        "date": "2020-11-15 16:00"
    },
    "29": {
        "id": 3,
        "site": " November Lunchtime 2020 ",
        "date": "2020-11-28 14:00"
    },
    "30": {
        "id": 3,
        "site": " December Challenge 2020 ",
        "date": "2020-12-04 09:30"
    },
    "31": {
        "id": 3,
        "site": " December Cook-Off 2020 ",
        "date": "2020-12-20 16:00"
    },
    "32": {
        "id": 3,
        "site": " December Lunchtime 2020 ",
        "date": "2020-12-26 14:00"
    }
}